{"moduleName":null,"summaries":[{"symbol":{"__symbol":0,"members":[]},"metadata":{"__symbolic":"class","members":{"yes":[{"__symbolic":"property","decorators":[{"__symbolic":"call","expression":{"__symbolic":"resolved","symbol":{"__symbol":1,"members":[]},"line":17,"character":3,"fileName":"src/components/select-bool/select-bool.ts"}}]}],"no":[{"__symbolic":"property","decorators":[{"__symbolic":"call","expression":{"__symbolic":"resolved","symbol":{"__symbol":1,"members":[]},"line":20,"character":3,"fileName":"src/components/select-bool/select-bool.ts"}}]}],"onBlur":[{"__symbolic":"method"}],"writeValue":[{"__symbolic":"method"}],"registerOnChange":[{"__symbolic":"method"}],"registerOnTouched":[{"__symbolic":"method"}]}},"type":{"summaryKind":1,"type":{"reference":{"__symbol":0,"members":[]},"diDeps":[],"lifecycleHooks":[]},"isComponent":true,"selector":"app-select-bool","exportAs":null,"inputs":{"yes":"yes","no":"no"},"outputs":{},"hostListeners":{},"hostProperties":{},"hostAttributes":{},"providers":[{"token":{"identifier":{"reference":{"__symbol":2,"members":[]}}},"useClass":null,"useFactory":null,"useExisting":{"identifier":{"reference":{"__symbol":0,"members":[]}}},"multi":true}],"viewProviders":[],"queries":[],"guards":{},"viewQueries":[],"entryComponents":[],"changeDetection":1,"template":{"ngContentSelectors":[],"encapsulation":2},"componentViewType":{"__symbol":3,"members":[]},"rendererType":{"__symbol":4,"members":[]},"componentFactory":{"__symbol":5,"members":[]}}}],"symbols":[{"__symbol":0,"name":"SelectBoolComponent","filePath":"./select-bool"},{"__symbol":1,"name":"Input","filePath":"@angular/core/core"},{"__symbol":2,"name":"NG_VALUE_ACCESSOR","filePath":"@angular/forms/forms"},{"__symbol":3,"name":"View_SelectBoolComponent_0","filePath":"./select-bool.ngfactory"},{"__symbol":4,"name":"RenderType_SelectBoolComponent","filePath":"./select-bool.ngfactory"},{"__symbol":5,"name":"SelectBoolComponentNgFactory","filePath":"./select-bool.ngfactory"}]}