[{"__symbolic":"module","version":4,"metadata":{"BaseReadFieldComponent":{"__symbolic":"class","decorators":[{"__symbolic":"call","expression":{"__symbolic":"reference","module":"@angular/core","name":"Component","line":5,"character":1},"arguments":[{"selector":"app-read-field","templateUrl":"read-field.html"}]}],"members":{"label":[{"__symbolic":"property","decorators":[{"__symbolic":"call","expression":{"__symbolic":"reference","module":"@angular/core","name":"Input","line":11,"character":3}}]}],"text":[{"__symbolic":"property","decorators":[{"__symbolic":"call","expression":{"__symbolic":"reference","module":"@angular/core","name":"Input","line":14,"character":3}}]}],"stretched":[{"__symbolic":"property","decorators":[{"__symbolic":"call","expression":{"__symbolic":"reference","module":"@angular/core","name":"Input","line":17,"character":3}}]}]}}}}]